[
  {
    "Segment": "GLOB",
    "Type": "Tec_Stat",
    "Code": "C",
    "Description": "Certification Due",
    "Sort_Order": 1,
    "UoM_Type": "NULL",
    "Last_Modified": "2011-09-30 07:19:13.520",
    "Last_Modified_By": "System",
    "Creation_Date": "2011-09-30 07:19:13.520",
    "Created_By": "System"
  },
  {
    "Segment": "GLOB",
    "Type": "Tec_Stat",
    "Code": "DC",
    "Description": "Due for Commissioning",
    "Sort_Order": 4,
    "UoM_Type": "NULL",
    "Last_Modified": "2011-03-11 07:44:57.957",
    "Last_Modified_By": "System",
    "Creation_Date": "2011-03-11 07:44:57.957",
    "Created_By": "System"
  },
  {
    "Segment": "GLOB",
    "Type": "Tec_Stat",
    "Code": "IV",
    "Description": "Inventory Test",
    "Sort_Order": 6,
    "UoM_Type": "NULL",
    "Last_Modified": "2015-06-07 08:04:12.387",
    "Last_Modified_By": "System",
    "Creation_Date": "2015-06-07 08:04:12.387",
    "Created_By": "System"
  },
  {
    "Segment": "GLOB",
    "Type": "Tec_Stat",
    "Code": "LTR",
    "Description": "Leak Test Results",
    "Sort_Order": 8,
    "UoM_Type": "NULL",
    "Last_Modified": "2015-06-07 08:04:12.370",
    "Last_Modified_By": "System",
    "Creation_Date": "2015-06-07 08:04:12.370",
    "Created_By": "System"
  },
  {
    "Segment": "GLOB",
    "Type": "Tec_Stat",
    "Code": "MD",
    "Description": "Mod Due",
    "Sort_Order": 5,
    "UoM_Type": "NULL",
    "Last_Modified": "2011-09-30 07:19:13.613",
    "Last_Modified_By": "System",
    "Creation_Date": "2011-09-30 07:19:13.613",
    "Created_By": "System"
  },
  {
    "Segment": "GLOB",
    "Type": "Tec_Stat",
    "Code": "MO",
    "Description": "Mod Overdue",
    "Sort_Order": 2,
    "UoM_Type": "NULL",
    "Last_Modified": "2011-09-30 07:19:13.543",
    "Last_Modified_By": "System",
    "Creation_Date": "2011-09-30 07:19:13.543",
    "Created_By": "System"
  },
  {
    "Segment": "GLOB",
    "Type": "Tec_Stat",
    "Code": "NO",
    "Description": "Non Operational",
    "Sort_Order": 13,
    "UoM_Type": "NULL",
    "Last_Modified": "2013-08-10 06:16:16.287",
    "Last_Modified_By": "System",
    "Creation_Date": "2013-08-10 06:16:16.287",
    "Created_By": "System"
  },
  {
    "Segment": "GLOB",
    "Type": "Tec_Stat",
    "Code": "O",
    "Description": "Operational",
    "Sort_Order": 19,
    "UoM_Type": "NULL",
    "Last_Modified": "2011-09-30 07:19:13.633",
    "Last_Modified_By": "System",
    "Creation_Date": "2011-09-30 07:19:13.633",
    "Created_By": "System"
  },
  {
    "Segment": "GLOB",
    "Type": "Tec_Stat",
    "Code": "QC",
    "Description": "Q. Check",
    "Sort_Order": 10,
    "UoM_Type": "NULL",
    "Last_Modified": "2011-09-30 07:19:14.310",
    "Last_Modified_By": "System",
    "Creation_Date": "2011-09-30 07:19:14.310",
    "Created_By": "System"
  },
  {
    "Segment": "GLOB",
    "Type": "Tec_Stat",
    "Code": "R",
    "Description": "Repair",
    "Sort_Order": 0,
    "UoM_Type": "NULL",
    "Last_Modified": "2011-09-30 07:19:13.570",
    "Last_Modified_By": "System",
    "Creation_Date": "2011-09-30 07:19:13.570",
    "Created_By": "System"
  },
  {
    "Segment": "GLOB",
    "Type": "Tec_Stat",
    "Code": "S",
    "Description": "Service",
    "Sort_Order": 12,
    "UoM_Type": "NULL",
    "Last_Modified": "2011-09-30 07:19:13.593",
    "Last_Modified_By": "System",
    "Creation_Date": "2011-09-30 07:19:13.593",
    "Created_By": "System"
  },
  {
    "Segment": "GLOB",
    "Type": "Tec_Stat",
    "Code": "SL",
    "Description": "Service Level",
    "Sort_Order": 9,
    "UoM_Type": "NULL",
    "Last_Modified": "2014-04-23 07:19:45.260",
    "Last_Modified_By": "System",
    "Creation_Date": "2014-04-23 07:19:45.260",
    "Created_By": "System"
  },
  {
    "Segment": "GLOB",
    "Type": "Tec_Stat",
    "Code": "T3",
    "Description": "STEM (T3)",
    "Sort_Order": 11,
    "UoM_Type": "NULL",
    "Last_Modified": "2011-09-30 07:19:14.333",
    "Last_Modified_By": "System",
    "Creation_Date": "2011-09-30 07:19:14.333",
    "Created_By": "System"
  },
  {
    "Segment": "GLOB",
    "Type": "Tec_Stat",
    "Code": "TA",
    "Description": "Tech Alert",
    "Sort_Order": 3,
    "UoM_Type": "NULL",
    "Last_Modified": "2011-09-30 07:19:14.290",
    "Last_Modified_By": "System",
    "Creation_Date": "2011-09-30 07:19:14.290",
    "Created_By": "System"
  },
  {
    "Segment": "GLOB",
    "Type": "Tec_Stat",
    "Code": "WT",
    "Description": "Wipe Test",
    "Sort_Order": 7,
    "UoM_Type": "NULL",
    "Last_Modified": "2015-06-07 08:04:12.377",
    "Last_Modified_By": "System",
    "Creation_Date": "2015-06-07 08:04:12.377",
    "Created_By": "System"
  }
]